atro_victoria/__init__.py
atro_victoria-0.0.8.dist-info/METADATA
atro_victoria-0.0.8.dist-info/WHEEL
atro_victoria-0.0.8.dist-info/RECORD
